<?xml version="1.0" encoding="utf-8"?>
<DayEntry xmlns:xsd="http://www.w3.org/2001/XMLSchema" xmlns:xsi="http://www.w3.org/2001/XMLSchema-instance" xmlns="urn:newtelligence-com:dasblog:runtime:data">
  <Date>2005-08-15T02:00:00.0000000+02:00</Date>
  <Entries>
    <Entry>
      <Content>&lt;P&gt;A very funny &lt;A href="http://www.hugi.is/hahradi/bigboxes.php?box_id=51208&amp;amp;f_id=1395"&gt;video&lt;/A&gt;.&lt;/P&gt;
&lt;P&gt;[Via &lt;A href="http://haacked.com/archive/2005/08/13/9388.aspx"&gt;Haacked&lt;/A&gt;]&lt;/P&gt;</Content>
      <Created>2005-08-15T03:36:28.0000000+02:00</Created>
      <Modified>2006-01-29T15:56:49.2827390+01:00</Modified>
      <EntryId>e945974d-e4c8-40bd-a46d-011ee76ef857</EntryId>
      <Description />
      <Title>Check it out</Title>
      <Categories>Fun Stuff</Categories>
      <Author>agross</Author>
      <IsPublic>true</IsPublic>
      <Syndicated>true</Syndicated>
      <ShowOnFrontPage>true</ShowOnFrontPage>
      <AllowComments>true</AllowComments>
      <Attachments />
      <Crossposts />
    </Entry>
  </Entries>
</DayEntry>